market-profile/__init__.py
market-profile/mktProfile.py
market-profile/profile_command_line.py
market_profile-0.1.1.dist-info/METADATA
market_profile-0.1.1.dist-info/RECORD
market_profile-0.1.1.dist-info/WHEEL
market_profile-0.1.1.dist-info/top_level.txt
mktProfile/__init__.py
mktProfile/profile_command_line.py
