Metadata-Version: 2.1
Name: market-profile
Version: 0.1.1
Summary: A library that generates Market Profile from OHLC data
Home-page: https://github.com/pranshu0210/market-profile
Author: Pranshu Dave
Author-email: pranshudave@gmail.com
License: MIT license
Keywords: python,finance,market profile,quant,stock,crypto
Platform: UNKNOWN
Classifier: Development Status :: 3 - Alpha
Classifier: Intended Audience :: Developers
Classifier: License :: OSI Approved :: MIT License
Classifier: Programming Language :: Python :: 3
Requires-Dist: numpy (>=1.13.0)
Requires-Dist: pandas (>=0.20.3)
